django_loader_dumper/__init__.py
django_loader_dumper/management/__init__.py
django_loader_dumper/management/commands/__init__.py
django_loader_dumper/management/commands/fixturedumper.py
django_loader_dumper/management/commands/fixtureloader.py
django_loader_dumper-1.0.3.dist-info/DESCRIPTION.rst
django_loader_dumper-1.0.3.dist-info/METADATA
django_loader_dumper-1.0.3.dist-info/RECORD
django_loader_dumper-1.0.3.dist-info/WHEEL
django_loader_dumper-1.0.3.dist-info/metadata.json
django_loader_dumper-1.0.3.dist-info/top_level.txt
